bed_lookup/__init__.py
bed_lookup/_bed_lookup.cpp
bed_lookup/_bed_lookup.cpython-39-darwin.so
bed_lookup/logme.py
python_bed_lookup-0.1.0.data/scripts/bed_location_lookup
python_bed_lookup-0.1.0.dist-info/LICENSE
python_bed_lookup-0.1.0.dist-info/METADATA
python_bed_lookup-0.1.0.dist-info/WHEEL
python_bed_lookup-0.1.0.dist-info/top_level.txt
python_bed_lookup-0.1.0.dist-info/RECORD
